jeometric/__init__.py
jeometric/data.py
jeometric/data_reader.py
jeometric/gnn.py
jeometric/ops.py
jeometric/util.py
jeometric-0.0.1.dev1.dist-info/LICENSE
jeometric-0.0.1.dev1.dist-info/METADATA
jeometric-0.0.1.dev1.dist-info/WHEEL
jeometric-0.0.1.dev1.dist-info/top_level.txt
jeometric-0.0.1.dev1.dist-info/RECORD
